{
  "metadata": {
    "soundFile": "D:\\SIH@025\\3DAvatar\\3DAvatar\\backend\\audios\\message_4.wav",
    "duration": 39.41
  },
  "mouthCues": [
    { "start": 0.00, "end": 0.04, "value": "X" },
    { "start": 0.04, "end": 0.10, "value": "B" },
    { "start": 0.10, "end": 0.16, "value": "C" },
    { "start": 0.16, "end": 0.23, "value": "B" },
    { "start": 0.23, "end": 0.51, "value": "C" },
    { "start": 0.51, "end": 0.79, "value": "B" },
    { "start": 0.79, "end": 0.93, "value": "C" },
    { "start": 0.93, "end": 1.14, "value": "B" },
    { "start": 1.14, "end": 1.21, "value": "G" },
    { "start": 1.21, "end": 1.28, "value": "C" },
    { "start": 1.28, "end": 1.42, "value": "B" },
    { "start": 1.42, "end": 1.49, "value": "C" },
    { "start": 1.49, "end": 1.56, "value": "B" },
    { "start": 1.56, "end": 1.63, "value": "G" },
    { "start": 1.63, "end": 1.70, "value": "E" },
    { "start": 1.70, "end": 1.84, "value": "H" },
    { "start": 1.84, "end": 1.98, "value": "C" },
    { "start": 1.98, "end": 2.06, "value": "A" },
    { "start": 2.06, "end": 2.16, "value": "B" },
    { "start": 2.16, "end": 2.23, "value": "E" },
    { "start": 2.23, "end": 2.37, "value": "F" },
    { "start": 2.37, "end": 2.44, "value": "C" },
    { "start": 2.44, "end": 2.86, "value": "B" },
    { "start": 2.86, "end": 3.14, "value": "F" },
    { "start": 3.14, "end": 3.21, "value": "B" },
    { "start": 3.21, "end": 3.35, "value": "F" },
    { "start": 3.35, "end": 3.49, "value": "C" },
    { "start": 3.49, "end": 3.70, "value": "B" },
    { "start": 3.70, "end": 3.87, "value": "X" },
    { "start": 3.87, "end": 4.12, "value": "B" },
    { "start": 4.12, "end": 4.26, "value": "F" },
    { "start": 4.26, "end": 4.47, "value": "B" },
    { "start": 4.47, "end": 4.54, "value": "C" },
    { "start": 4.54, "end": 4.75, "value": "B" },
    { "start": 4.75, "end": 4.96, "value": "F" },
    { "start": 4.96, "end": 5.10, "value": "B" },
    { "start": 5.10, "end": 5.24, "value": "F" },
    { "start": 5.24, "end": 5.31, "value": "E" },
    { "start": 5.31, "end": 5.38, "value": "H" },
    { "start": 5.38, "end": 5.45, "value": "D" },
    { "start": 5.45, "end": 5.66, "value": "B" },
    { "start": 5.66, "end": 5.73, "value": "F" },
    { "start": 5.73, "end": 5.80, "value": "C" },
    { "start": 5.80, "end": 5.94, "value": "B" },
    { "start": 5.94, "end": 6.08, "value": "C" },
    { "start": 6.08, "end": 6.36, "value": "B" },
    { "start": 6.36, "end": 6.40, "value": "C" },
    { "start": 6.40, "end": 6.54, "value": "B" },
    { "start": 6.54, "end": 6.65, "value": "A" },
    { "start": 6.65, "end": 6.72, "value": "C" },
    { "start": 6.72, "end": 6.78, "value": "B" },
    { "start": 6.78, "end": 6.85, "value": "C" },
    { "start": 6.85, "end": 6.99, "value": "B" },
    { "start": 6.99, "end": 7.06, "value": "H" },
    { "start": 7.06, "end": 7.27, "value": "C" },
    { "start": 7.27, "end": 7.34, "value": "B" },
    { "start": 7.34, "end": 7.55, "value": "C" },
    { "start": 7.55, "end": 7.62, "value": "B" },
    { "start": 7.62, "end": 7.83, "value": "C" },
    { "start": 7.83, "end": 7.90, "value": "E" },
    { "start": 7.90, "end": 7.97, "value": "C" },
    { "start": 7.97, "end": 8.32, "value": "B" },
    { "start": 8.32, "end": 8.53, "value": "C" },
    { "start": 8.53, "end": 8.67, "value": "B" },
    { "start": 8.67, "end": 8.74, "value": "G" },
    { "start": 8.74, "end": 9.09, "value": "B" },
    { "start": 9.09, "end": 9.30, "value": "F" },
    { "start": 9.30, "end": 9.72, "value": "B" },
    { "start": 9.72, "end": 9.79, "value": "C" },
    { "start": 9.79, "end": 10.09, "value": "E" },
    { "start": 10.09, "end": 10.49, "value": "B" },
    { "start": 10.49, "end": 10.56, "value": "C" },
    { "start": 10.56, "end": 10.91, "value": "B" },
    { "start": 10.91, "end": 10.98, "value": "C" },
    { "start": 10.98, "end": 11.06, "value": "B" },
    { "start": 11.06, "end": 11.10, "value": "A" },
    { "start": 11.10, "end": 11.18, "value": "B" },
    { "start": 11.18, "end": 11.26, "value": "A" },
    { "start": 11.26, "end": 11.33, "value": "C" },
    { "start": 11.33, "end": 11.47, "value": "B" },
    { "start": 11.47, "end": 11.54, "value": "E" },
    { "start": 11.54, "end": 11.82, "value": "F" },
    { "start": 11.82, "end": 11.89, "value": "B" },
    { "start": 11.89, "end": 12.03, "value": "C" },
    { "start": 12.03, "end": 12.38, "value": "B" },
    { "start": 12.38, "end": 12.52, "value": "A" },
    { "start": 12.52, "end": 12.57, "value": "F" },
    { "start": 12.57, "end": 12.68, "value": "C" },
    { "start": 12.68, "end": 13.12, "value": "B" },
    { "start": 13.12, "end": 13.19, "value": "F" },
    { "start": 13.19, "end": 13.33, "value": "D" },
    { "start": 13.33, "end": 13.75, "value": "B" },
    { "start": 13.75, "end": 13.82, "value": "F" },
    { "start": 13.82, "end": 13.96, "value": "D" },
    { "start": 13.96, "end": 14.37, "value": "B" },
    { "start": 14.37, "end": 14.48, "value": "F" },
    { "start": 14.48, "end": 14.62, "value": "C" },
    { "start": 14.62, "end": 14.90, "value": "B" },
    { "start": 14.90, "end": 15.11, "value": "C" },
    { "start": 15.11, "end": 15.38, "value": "A" },
    { "start": 15.38, "end": 15.45, "value": "E" },
    { "start": 15.45, "end": 15.52, "value": "B" },
    { "start": 15.52, "end": 15.59, "value": "C" },
    { "start": 15.59, "end": 15.73, "value": "H" },
    { "start": 15.73, "end": 15.80, "value": "C" },
    { "start": 15.80, "end": 15.88, "value": "A" },
    { "start": 15.88, "end": 16.02, "value": "C" },
    { "start": 16.02, "end": 16.16, "value": "B" },
    { "start": 16.16, "end": 16.23, "value": "G" },
    { "start": 16.23, "end": 16.37, "value": "C" },
    { "start": 16.37, "end": 16.51, "value": "B" },
    { "start": 16.51, "end": 16.58, "value": "C" },
    { "start": 16.58, "end": 16.72, "value": "F" },
    { "start": 16.72, "end": 16.93, "value": "B" },
    { "start": 16.93, "end": 17.01, "value": "A" },
    { "start": 17.01, "end": 17.19, "value": "C" },
    { "start": 17.19, "end": 17.40, "value": "B" },
    { "start": 17.40, "end": 17.68, "value": "C" },
    { "start": 17.68, "end": 17.75, "value": "B" },
    { "start": 17.75, "end": 17.82, "value": "G" },
    { "start": 17.82, "end": 17.89, "value": "C" },
    { "start": 17.89, "end": 18.10, "value": "F" },
    { "start": 18.10, "end": 18.24, "value": "D" },
    { "start": 18.24, "end": 18.80, "value": "B" },
    { "start": 18.80, "end": 19.15, "value": "F" },
    { "start": 19.15, "end": 19.22, "value": "G" },
    { "start": 19.22, "end": 19.50, "value": "B" },
    { "start": 19.50, "end": 19.57, "value": "F" },
    { "start": 19.57, "end": 19.71, "value": "E" },
    { "start": 19.71, "end": 19.78, "value": "G" },
    { "start": 19.78, "end": 19.99, "value": "C" },
    { "start": 19.99, "end": 20.06, "value": "B" },
    { "start": 20.06, "end": 20.13, "value": "C" },
    { "start": 20.13, "end": 20.27, "value": "E" },
    { "start": 20.27, "end": 20.62, "value": "B" },
    { "start": 20.62, "end": 20.97, "value": "F" },
    { "start": 20.97, "end": 21.04, "value": "B" },
    { "start": 21.04, "end": 21.12, "value": "A" },
    { "start": 21.12, "end": 21.23, "value": "D" },
    { "start": 21.23, "end": 21.30, "value": "C" },
    { "start": 21.30, "end": 21.38, "value": "A" },
    { "start": 21.38, "end": 21.42, "value": "B" },
    { "start": 21.42, "end": 21.53, "value": "D" },
    { "start": 21.53, "end": 21.60, "value": "C" },
    { "start": 21.60, "end": 21.88, "value": "B" },
    { "start": 21.88, "end": 21.96, "value": "A" },
    { "start": 21.96, "end": 22.02, "value": "C" },
    { "start": 22.02, "end": 22.21, "value": "B" },
    { "start": 22.21, "end": 22.28, "value": "E" },
    { "start": 22.28, "end": 22.77, "value": "B" },
    { "start": 22.77, "end": 22.89, "value": "A" },
    { "start": 22.89, "end": 22.99, "value": "B" },
    { "start": 22.99, "end": 23.18, "value": "C" },
    { "start": 23.18, "end": 23.23, "value": "E" },
    { "start": 23.23, "end": 23.48, "value": "F" },
    { "start": 23.48, "end": 23.69, "value": "B" },
    { "start": 23.69, "end": 23.76, "value": "F" },
    { "start": 23.76, "end": 23.83, "value": "C" },
    { "start": 23.83, "end": 24.59, "value": "B" },
    { "start": 24.59, "end": 24.64, "value": "C" },
    { "start": 24.64, "end": 24.78, "value": "B" },
    { "start": 24.78, "end": 24.86, "value": "A" },
    { "start": 24.86, "end": 25.01, "value": "H" },
    { "start": 25.01, "end": 25.08, "value": "C" },
    { "start": 25.08, "end": 25.22, "value": "B" },
    { "start": 25.22, "end": 25.36, "value": "F" },
    { "start": 25.36, "end": 25.50, "value": "D" },
    { "start": 25.50, "end": 25.78, "value": "B" },
    { "start": 25.78, "end": 25.99, "value": "F" },
    { "start": 25.99, "end": 26.27, "value": "B" },
    { "start": 26.27, "end": 26.34, "value": "F" },
    { "start": 26.34, "end": 26.41, "value": "B" },
    { "start": 26.41, "end": 26.48, "value": "C" },
    { "start": 26.48, "end": 26.55, "value": "E" },
    { "start": 26.55, "end": 26.64, "value": "A" },
    { "start": 26.64, "end": 26.96, "value": "C" },
    { "start": 26.96, "end": 27.03, "value": "B" },
    { "start": 27.03, "end": 27.17, "value": "C" },
    { "start": 27.17, "end": 27.31, "value": "B" },
    { "start": 27.31, "end": 27.39, "value": "A" },
    { "start": 27.39, "end": 27.60, "value": "D" },
    { "start": 27.60, "end": 27.74, "value": "B" },
    { "start": 27.74, "end": 27.88, "value": "F" },
    { "start": 27.88, "end": 27.95, "value": "D" },
    { "start": 27.95, "end": 28.23, "value": "B" },
    { "start": 28.23, "end": 28.44, "value": "F" },
    { "start": 28.44, "end": 28.72, "value": "B" },
    { "start": 28.72, "end": 28.79, "value": "F" },
    { "start": 28.79, "end": 28.93, "value": "C" },
    { "start": 28.93, "end": 29.07, "value": "E" },
    { "start": 29.07, "end": 29.84, "value": "B" },
    { "start": 29.84, "end": 30.12, "value": "C" },
    { "start": 30.12, "end": 30.68, "value": "B" },
    { "start": 30.68, "end": 30.82, "value": "G" },
    { "start": 30.82, "end": 30.89, "value": "C" },
    { "start": 30.89, "end": 30.96, "value": "B" },
    { "start": 30.96, "end": 31.04, "value": "A" },
    { "start": 31.04, "end": 31.22, "value": "B" },
    { "start": 31.22, "end": 31.29, "value": "F" },
    { "start": 31.29, "end": 31.36, "value": "C" },
    { "start": 31.36, "end": 31.50, "value": "B" },
    { "start": 31.50, "end": 31.57, "value": "C" },
    { "start": 31.57, "end": 31.78, "value": "B" },
    { "start": 31.78, "end": 31.92, "value": "C" },
    { "start": 31.92, "end": 32.06, "value": "B" },
    { "start": 32.06, "end": 32.20, "value": "F" },
    { "start": 32.20, "end": 32.27, "value": "B" },
    { "start": 32.27, "end": 32.48, "value": "C" },
    { "start": 32.48, "end": 32.55, "value": "G" },
    { "start": 32.55, "end": 32.69, "value": "F" },
    { "start": 32.69, "end": 32.76, "value": "C" },
    { "start": 32.76, "end": 33.32, "value": "B" },
    { "start": 33.32, "end": 33.60, "value": "F" },
    { "start": 33.60, "end": 33.67, "value": "B" },
    { "start": 33.67, "end": 33.87, "value": "F" },
    { "start": 33.87, "end": 33.95, "value": "E" },
    { "start": 33.95, "end": 34.02, "value": "H" },
    { "start": 34.02, "end": 34.30, "value": "C" },
    { "start": 34.30, "end": 34.37, "value": "E" },
    { "start": 34.37, "end": 34.51, "value": "F" },
    { "start": 34.51, "end": 35.00, "value": "B" },
    { "start": 35.00, "end": 35.08, "value": "A" },
    { "start": 35.08, "end": 35.33, "value": "B" },
    { "start": 35.33, "end": 35.68, "value": "F" },
    { "start": 35.68, "end": 35.82, "value": "B" },
    { "start": 35.82, "end": 35.89, "value": "C" },
    { "start": 35.89, "end": 35.96, "value": "B" },
    { "start": 35.96, "end": 36.04, "value": "A" },
    { "start": 36.04, "end": 36.16, "value": "C" },
    { "start": 36.16, "end": 36.23, "value": "E" },
    { "start": 36.23, "end": 36.37, "value": "B" },
    { "start": 36.37, "end": 36.51, "value": "G" },
    { "start": 36.51, "end": 36.58, "value": "E" },
    { "start": 36.58, "end": 36.72, "value": "F" },
    { "start": 36.72, "end": 36.86, "value": "B" },
    { "start": 36.86, "end": 36.93, "value": "G" },
    { "start": 36.93, "end": 37.07, "value": "C" },
    { "start": 37.07, "end": 37.21, "value": "B" },
    { "start": 37.21, "end": 37.29, "value": "A" },
    { "start": 37.29, "end": 37.44, "value": "E" },
    { "start": 37.44, "end": 37.51, "value": "C" },
    { "start": 37.51, "end": 37.65, "value": "B" },
    { "start": 37.65, "end": 37.86, "value": "C" },
    { "start": 37.86, "end": 37.93, "value": "B" },
    { "start": 37.93, "end": 38.07, "value": "G" },
    { "start": 38.07, "end": 38.21, "value": "D" },
    { "start": 38.21, "end": 38.35, "value": "H" },
    { "start": 38.35, "end": 38.42, "value": "G" },
    { "start": 38.42, "end": 38.70, "value": "B" },
    { "start": 38.70, "end": 38.84, "value": "C" },
    { "start": 38.84, "end": 38.91, "value": "B" },
    { "start": 38.91, "end": 39.05, "value": "E" },
    { "start": 39.05, "end": 39.19, "value": "B" },
    { "start": 39.19, "end": 39.33, "value": "C" },
    { "start": 39.33, "end": 39.40, "value": "B" },
    { "start": 39.40, "end": 39.41, "value": "X" }
  ]
}
