{
  "metadata": {
    "soundFile": "D:\\SIH@025\\3DAvatar\\3DAvatar\\backend\\audios\\video_narration_session_1758655778581_imotb81n6.wav",
    "duration": 4.96
  },
  "mouthCues": [
    { "start": 0.00, "end": 0.04, "value": "X" },
    { "start": 0.04, "end": 0.10, "value": "B" },
    { "start": 0.10, "end": 0.22, "value": "C" },
    { "start": 0.22, "end": 0.30, "value": "A" },
    { "start": 0.30, "end": 0.39, "value": "B" },
    { "start": 0.39, "end": 0.46, "value": "C" },
    { "start": 0.46, "end": 0.53, "value": "B" },
    { "start": 0.53, "end": 0.61, "value": "A" },
    { "start": 0.61, "end": 0.73, "value": "H" },
    { "start": 0.73, "end": 0.87, "value": "C" },
    { "start": 0.87, "end": 1.29, "value": "B" },
    { "start": 1.29, "end": 1.57, "value": "E" },
    { "start": 1.57, "end": 1.71, "value": "B" },
    { "start": 1.71, "end": 1.85, "value": "G" },
    { "start": 1.85, "end": 1.92, "value": "D" },
    { "start": 1.92, "end": 1.99, "value": "C" },
    { "start": 1.99, "end": 2.06, "value": "B" },
    { "start": 2.06, "end": 2.13, "value": "C" },
    { "start": 2.13, "end": 2.21, "value": "A" },
    { "start": 2.21, "end": 2.31, "value": "D" },
    { "start": 2.31, "end": 2.36, "value": "C" },
    { "start": 2.36, "end": 2.44, "value": "A" },
    { "start": 2.44, "end": 2.73, "value": "B" },
    { "start": 2.73, "end": 2.94, "value": "F" },
    { "start": 2.94, "end": 3.22, "value": "B" },
    { "start": 3.22, "end": 3.29, "value": "C" },
    { "start": 3.29, "end": 3.36, "value": "E" },
    { "start": 3.36, "end": 3.43, "value": "G" },
    { "start": 3.43, "end": 3.64, "value": "B" },
    { "start": 3.64, "end": 3.78, "value": "E" },
    { "start": 3.78, "end": 3.85, "value": "H" },
    { "start": 3.85, "end": 3.92, "value": "B" },
    { "start": 3.92, "end": 3.99, "value": "G" },
    { "start": 3.99, "end": 4.13, "value": "C" },
    { "start": 4.13, "end": 4.21, "value": "A" },
    { "start": 4.21, "end": 4.53, "value": "E" },
    { "start": 4.53, "end": 4.60, "value": "B" },
    { "start": 4.60, "end": 4.96, "value": "X" }
  ]
}
